utoolbox_image-0.0.2.data/purelib/utoolbox/exposure/__init__.py
utoolbox_image-0.0.2.data/purelib/utoolbox/filters/__init__.py
utoolbox_image-0.0.2.data/purelib/utoolbox/restoration/__init__.py
utoolbox_image-0.0.2.data/purelib/utoolbox/util/preview.py
utoolbox_image-0.0.2.dist-info/LICENSE.md
utoolbox_image-0.0.2.dist-info/METADATA
utoolbox_image-0.0.2.dist-info/WHEEL
utoolbox_image-0.0.2.dist-info/entry_points.txt
utoolbox_image-0.0.2.dist-info/top_level.txt
utoolbox_image-0.0.2.dist-info/zip-safe
utoolbox_image-0.0.2.dist-info/RECORD
